git_crecord/__init__.py
git_crecord/chunk_selector.py
git_crecord/crecord_core.py
git_crecord/crpatch.py
git_crecord/encoding.py
git_crecord/gitrepo.py
git_crecord/main.py
git_crecord/util.py
git_crecord-20201025.0.data/data/share/doc/git-crecord/CONTRIBUTORS
git_crecord-20201025.0.data/data/share/doc/git-crecord/COPYING
git_crecord-20201025.0.data/data/share/doc/git-crecord/README.rst
git_crecord-20201025.0.data/data/share/doc/git-crecord/git-crecord.rst
git_crecord-20201025.0.data/data/share/doc/git-crecord/screenshot.png
git_crecord-20201025.0.data/data/share/man/man1/git-crecord.1
git_crecord-20201025.0.dist-info/COPYING
git_crecord-20201025.0.dist-info/METADATA
git_crecord-20201025.0.dist-info/WHEEL
git_crecord-20201025.0.dist-info/entry_points.txt
git_crecord-20201025.0.dist-info/top_level.txt
git_crecord-20201025.0.dist-info/RECORD
