Metadata-Version: 2.1
Name: git-crecord
Version: 20201025.0
Summary: interactively select chunks to commit with Git
Home-page: https://github.com/andrewshadura/git-crecord
Author: Andrej Shadura
Author-email: andrew@shadura.me
License: GPL-2+
Platform: UNKNOWN
Classifier: Development Status :: 4 - Beta
Classifier: Environment :: Console :: Curses
Classifier: Intended Audience :: Developers
Classifier: License :: OSI Approved :: GNU General Public License (GPL)
Classifier: Operating System :: OS Independent
Classifier: Programming Language :: Python
Classifier: Programming Language :: Python :: 3.6
Classifier: Programming Language :: Python :: 3.7
Classifier: Programming Language :: Python :: 3.8
Classifier: Topic :: Software Development :: Version Control
Requires-Python: >=3.6
